Metadata-Version: 1.0
Name: myPC-distributions
Version: 0.2
Summary: Gaussian and Binomial distributions
Home-page: UNKNOWN
Author: Pedro Carvajal
Author-email: peterven25@gmail.com
License: UNKNOWN
Platform: UNKNOWN
